dwipe/DeviceInfo.py
dwipe/DiskWipe.py
dwipe/DrivePreChecker.py
dwipe/FirmwareWipeTask.py
dwipe/LsblkMonitor.py
dwipe/PersistentState.py
dwipe/Prereqs.py
dwipe/StructuredLogger.py
dwipe/ToolManager.py
dwipe/Utils.py
dwipe/VerifyTask.py
dwipe/WipeJob.py
dwipe/WipeTask.py
dwipe/WriteTask.py
dwipe/__init__.py
dwipe/main.py
dwipe-2.0.2.dist-info/entry_points.txt
dwipe-2.0.2.dist-info/licenses/LICENSE
dwipe-2.0.2.dist-info/WHEEL
dwipe-2.0.2.dist-info/METADATA
dwipe-2.0.2.dist-info/RECORD
