Metadata-Version: 2.4
Name: dwipe
Version: 2.0.2
Summary: A tool to wipe disks and partitions for Linux
Keywords: disk,partition,wipe,clean,scrub
Author-email: Joe Defen <joedef@google.com>
Requires-Python: >=3.8
Classifier: Programming Language :: Python :: 3
Classifier: License :: OSI Approved :: MIT License
Classifier: Operating System :: POSIX :: Linux
License-File: LICENSE
Requires-Dist: console-window == 1.4.2
Project-URL: Bug Tracker, https://github.com/joedefen/dwipe/issues
Project-URL: Homepage, https://github.com/joedefen/dwipe
